sbi4onnx/__init__.py
sbi4onnx/__main__.py
sbi4onnx/onnx_batchsize_initialize.py
sbi4onnx-1.0.7.dist-info/LICENSE
sbi4onnx-1.0.7.dist-info/METADATA
sbi4onnx-1.0.7.dist-info/WHEEL
sbi4onnx-1.0.7.dist-info/entry_points.txt
sbi4onnx-1.0.7.dist-info/top_level.txt
sbi4onnx-1.0.7.dist-info/RECORD
