Metadata-Version: 2.1
Name: sbi4onnx
Version: 1.0.7
Summary: A very simple script that only initializes the batch size of ONNX. Simple Batchsize Initialization for ONNX.
Home-page: https://github.com/PINTO0309/sbi4onnx
Author: Katsuya Hyodo
Author-email: rmsdh122@yahoo.co.jp
License: MIT License
Platform: linux
Platform: unix
Requires-Python: >=3.6
License-File: LICENSE
